LICENSE
MANIFEST.in
setup.py
django_debugging/__init__.py
django_debugging.egg-info/PKG-INFO
django_debugging.egg-info/SOURCES.txt
django_debugging.egg-info/dependency_links.txt
django_debugging.egg-info/requires.txt
django_debugging.egg-info/top_level.txt
django_debugging/management/__init__.py
django_debugging/management/commands/__init__.py
django_debugging/management/commands/runserver_plus.py