Metadata-Version: 1.0
Name: django-debugging
Version: 0.1a2
Summary: Debugging utilities for Django.
Home-page: https://bitbucket.org/nextscreenlabs/django-debugging
Author: Jason Christa
Author-email: jason@zeitcode.com
License: UNKNOWN
Platform: UNKNOWN
Classifier: Environment :: Web Environment
Classifier: License :: OSI Approved :: BSD License
Classifier: Framework :: Django
Classifier: Programming Language :: Python
